strangeworks_optimization_models/__init__.py
strangeworks_optimization_models/converter_models.py
strangeworks_optimization_models/parameter_models.py
strangeworks_optimization_models/problem_models.py
strangeworks_optimization_models/py.typed
strangeworks_optimization_models/solution_models.py
strangeworks_optimization_models/solver_models.py
strangeworks_optimization_models/strangeworks_models.py
strangeworks_optimization_models/mps/LICENSE.txt
strangeworks_optimization_models/mps/__init__.py
strangeworks_optimization_models/mps/bqm_converter.py
strangeworks_optimization_models/mps/load.py
strangeworks_optimization_models/mps/pysmps_loader.py
strangeworks_optimization_models-0.1.68.dist-info/METADATA
strangeworks_optimization_models-0.1.68.dist-info/WHEEL
strangeworks_optimization_models-0.1.68.dist-info/RECORD
