Metadata-Version: 2.4
Name: strangeworks-optimization-models
Version: 0.1.68
Summary: Pydantic models for strangeworks optimization SDK and application
Author-email: Strange Devs <hello@strangeworks.com>
License-Expression: Apache-2.0
Requires-Python: <3.14,>=3.10
Requires-Dist: dimod<0.13,>=0.12.12
Requires-Dist: dwave-system<2,>=1.25.0
Requires-Dist: furo>=2025.9.25
Requires-Dist: jijmodeling>=1.12.4
Requires-Dist: myst-parser>=4.0.1
Requires-Dist: numpy>=1.20.0
Requires-Dist: numpydoc>=1.9.0
Requires-Dist: pyqubo<2,>=1.4.0
Requires-Dist: pyscipopt<6,>=5.1.1
Requires-Dist: sphinx>=8.1.3
